SeleniumWireLibrary/__init__.py
SeleniumWireLibrary/version.py
SeleniumWireLibrary/wire.py
robotframework_seleniumwire-0.1.1.dist-info/LICENSE
robotframework_seleniumwire-0.1.1.dist-info/METADATA
robotframework_seleniumwire-0.1.1.dist-info/WHEEL
robotframework_seleniumwire-0.1.1.dist-info/top_level.txt
robotframework_seleniumwire-0.1.1.dist-info/RECORD
