Metadata-Version: 2.1
Name: robotframework-seleniumwire
Version: 0.1.1
Summary: Robot Framework keyword library wrapper around selenium-wire library
Home-page: https://github.com/adiralashiva8/robotframework-seleniumwire
Author: Shiva Adirala
Author-email: adiralashiva8@gmail.com
License: MIT
Keywords: robotframework testing automation selenium-wire
Platform: any
Classifier: Operating System :: OS Independent
Classifier: Programming Language :: Python
Classifier: Topic :: Software Development :: Testing
License-File: LICENSE
Requires-Dist: robotframework
Requires-Dist: selenium
Requires-Dist: selenium-wire
